Metadata-Version: 2.4
Name: dify_plugin_zhlx
Version: 0.4.5
Summary: Dify Plugin SDK
Author-email: langgenius <hello@dify.ai>
License: Apache2.0
Project-URL: Homepage, https://github.com/langgenius/dify-plugin-sdks.git
Keywords: dify,plugin,sdk,zhlx
Requires-Python: >=3.11
License-File: LICENSE
Requires-Dist: Flask~=3.0.3
Requires-Dist: Werkzeug~=3.0.3
Requires-Dist: dpkt~=1.9.8
Requires-Dist: gevent~=25.5.1
Requires-Dist: httpx~=0.28.1
Requires-Dist: pydantic_settings<3.0.0,>=2.5.0
Requires-Dist: pydantic>=2.8.2
Requires-Dist: pyyaml~=6.0.1
Requires-Dist: requests~=2.32.3
Requires-Dist: socksio==1.0.0
Requires-Dist: tiktoken~=0.8.0
Requires-Dist: yarl<2.0,>=1.9.4
Requires-Dist: packaging>=25.0
Dynamic: license-file
